
 [
   {
    "photo1": "https://upload.wikimedia.org/wikipedia/fr/thumb/c/cd/Bunyodkor_FK_Logo.png/250px-Bunyodkor_FK_Logo.png",
    "name1": "Bunyodkor",
    "photo2": "https://upload.wikimedia.org/wikipedia/fr/thumb/7/71/Logo_HB_Koge.svg/langfr-250px-Logo_HB_Koge.svg.png",
    "name2": "HB Kogo ",
    "champ": "Matchs amicaux des clubs",
    "heure": "10H30",
    "date": "10/02/2026",
    "pro": "Total: (+2.5)"
  },
   {
    "photo1": "https://encrypted-tbn0.gstatic.com/images?q=tbn:ANd9GcSIzxwUygmPgJCYdUzGBqGvJC-RX4bJkhUgpA&s",
    "name1": "Spartak Moscou",
    "photo2": "https://encrypted-tbn0.gstatic.com/images?q=tbn:ANd9GcSKRtORhcRjxYcB7V-HC16t6cPkqWqoY3dsBA&s",
    "name2": "Astana",
    "champ": "Matchs amicaux des clubs",
    "heure": "13H00",
    "date": "10/02/2026",
    "pro": "V1"
  },
    {
    "photo1": "https://upload.wikimedia.org/wikipedia/fr/thumb/2/26/Sutjeska.png/200px-Sutjeska.png",
    "name1": "Sutjeska Niksic",
    "photo2": "https://upload.wikimedia.org/wikipedia/de/thumb/1/18/FK_Jezero_Plav_logo.svg/250px-FK_Jezero_Plav_logo.svg.png",
    "name2": "Jezero Plav",
    "champ": "Matchs amicaux des clubs",
    "heure": "13H00",
    "date": "10/02/2026",
    "pro": "Total: (+2.5)"
  },
  {
    "photo1": "https://upload.wikimedia.org/wikipedia/uk/c/ca/%D0%9B%D0%BE%D0%B3%D0%BE%D1%82%D0%B8%D0%BF_%D0%A4%D0%9A_%C2%AB%D0%9B%D0%9D%D0%97%C2%BB_%28%D0%A7%D0%B5%D1%80%D0%BA%D0%B0%D1%81%D0%B8%29.png",
    "name1": "LNZ",
    "photo2": "https://upload.wikimedia.org/wikipedia/fr/thumb/6/63/Logo_Chakhtar_Donetsk.svg/langfr-250px-Logo_Chakhtar_Donetsk.svg.png",
    "name2": "Chakhtar Donetsk",
    "champ": "Matchs amicaux des clubs",
    "heure": "14H00",
    "date": "10/02/2026",
    "pro": "V2"
  },
    {
    "photo1": "https://encrypted-tbn0.gstatic.com/images?q=tbn:ANd9GcQOsgnQCBzo_bcP1kJ7xl1sdZBg_GVkfaGr4w&s",
    "name1": "Esbjerg FB",
    "photo2": "https://upload.wikimedia.org/wikipedia/fr/thumb/2/28/Zimbru-Chisinau.png/225px-Zimbru-Chisinau.png",
    "name2": "Zimbru Chisinau",
    "champ": "Matchs amicaux des clubs",
    "heure": "14H00",
    "date": "10/02/2026",
    "pro": "Deux équipe vont marquer: OUI"
  },
    {
    "photo1": "https://upload.wikimedia.org/wikipedia/fr/4/44/Polissia_Jytomyr_logo_%282024%29.svg",
    "name1": "Polissya Jytomyr",
    "photo2": "https://upload.wikimedia.org/wikipedia/fr/6/6f/XHamster_logo_2016.png",
    "name2": "Halmstards",
    "champ": "Matchs amicaux des clubs",
    "heure": "16H00",
    "date": "10/02/2026",
    "pro": "Total: (+2.5)"
  },
  {
    "photo1": "https://upload.wikimedia.org/wikipedia/fr/thumb/f/f9/AGF_Aarhus_%28logo%29.svg/1280px-AGF_Aarhus_%28logo%29.svg.png",
    "name1": "AGF Arthus",
    "photo2": "https://encrypted-tbn0.gstatic.com/images?q=tbn:ANd9GcSUaxOSXA8q_EBLICAoVNXDpKOIAoWhYFRxRw&s",
    "name2": "Odense",
    "champ": "Championat du Danemark. Superliga",
    "heure": "20H00",
    "date": "09/02/2026",
    "pro": "1X Et TP(1.5) - OUI"
  }
]
